{
  "cale_galerie": "resurse/imagini/galerie",
  "imagini": [
    {
      "cale_imagine": "canon5dmk4.jpg",
      "titlu": "Canon EOS 5D MKIV",
      "timp": "00:00-23:59",
      "alt": "camera foto Canon EOS 5D MKIV",
      "galerie-animata": "true"
    },
    {
      "cale_imagine": "canon-1300d.jpg",
      "titlu": "Canon EOS 1300D",
      "timp": "08:00-14:00",
      "galerie-animata": true
    },
    {
      "cale_imagine": "canon-dslr.jpg",
      "titlu": "DSLR Canon",
      "timp": "10:00-19:00",
      "atribuire": "Foto de Indra Projects pe Unsplash",
      "galerie-animata": true
    },
    {
        "cale_imagine": "canon-ixus60.jpg",
        "titlu": "Canon Ixus 60",
        "timp": "10:00-13:00",
        "galerie-animata": true
    },
    {
        "cale_imagine": "canonr6.jpg",
        "titlu": "Canon R6",
        "timp": "00:00-14:00",
        "galerie-animata": true
    },
    {
        "cale_imagine": "compact-camera.jpg",
        "titlu": "Camera compacta",
        "timp": "8:00-14:00",
        "galerie-animata": true
    },
    {
        "cale_imagine": "fuji-x100.jpg",
        "titlu": "Fujifilm X-100",
        "timp": "14:00-23:59",
        "galerie-animata": true
    },
    {
        "cale_imagine": "fuji-xe3.jpg",
        "titlu": "Fujifilm X-E3",
        "timp": "14:00-23:59",
        "galerie-animata": true
    },
    {
        "cale_imagine": "fuji-xt.jpg",
        "titlu": "Fujifilm XT",
        "timp": "8:00-20:00",
        "galerie-animata": true
    },
    {
        "cale_imagine": "fuji-xta.jpg",
        "titlu": "Fujifilm XT",
        "timp": "00:00-23:59",
        "galerie-animata": true
    },
    {
        "cale_imagine": "olympus-omd.jpg",
        "titlu": "Olympus OM-D",
        "timp": "00:00-23:59",
        "galerie-animata": true
    },
    {
        "cale_imagine": "samsung-sd.jpg",
        "titlu": "Carduri SD",
        "timp": "00:00-23:59",
        "galerie-animata": true
    },
    {
        "cale_imagine": "sony-a7r2.jpg",
        "titlu": "Sony A7R",
        "timp": "00:00-23:59",
        "galerie-animata": true
    },
    {
        "cale_imagine": "sony-a73.jpg",
        "titlu": "Sony A7III",
        "timp": "00:00-23:59",
        "galerie-animata": true
    }
  ]
}